[
  {
    "id": 1,
    "brewery": "Baerlic Brewing Company",
    "name": "Altera",
    "region": "Oregon",
    "style": "North West Red Ale"
  },
  {
    "id": 2,
    "brewery": "Baerlic Brewing Company",
    "name": "Noble",
    "region": "Oregon",
    "style": "Oatmeal Stout"
  },
  {
    "id": 3,
    "brewery": "Boneyard Beer",
    "name": "Notorious IPA3",
    "region": "Oregon",
    "style": "Triple IPA"
  },
  {
    "id": 4,
    "brewery": "Boneyard Beer",
    "name": "Diablo Rojo",
    "region": "Oregon",
    "style": "American Red Ale"
  },
  {
    "id": 5,
    "brewery": "Breakside Brewery",
    "name": "Helles",
    "region": "Oregon",
    "style": "German Helles w. Cucumbers"
  },
  {
    "id": 6,
    "brewery": "Breakside Brewery",
    "name": "Passionfruit Sour",
    "region": "Oregon",
    "style": "Sour Ale w. Habanero"
  },
  {
    "id": 7,
    "brewery": "Brewers Union Local 180",
    "name": "Wotcha A La Sorachi",
    "region": "Oregon",
    "style": "Best Bitter"
  },
  {
    "id": 8,
    "brewery": "Buoy Beer Company",
    "name": "Buoy IPA",
    "region": "Oregon",
    "style": "American IPA"
  },
  {
    "id": 9,
    "brewery": "Buoy Beer Company",
    "name": "Buoy Red Ale",
    "region": "Oregon",
    "style": "North West Red Ale"
  },
  {
    "id": 10,
    "brewery": "Burnside Brewing Co",
    "name": "Thundarr The Bavarian",
    "region": "Oregon",
    "style": "Weizenbock"
  },
  {
    "id": 11,
    "brewery": "Burnside Brewing Co",
    "name": "Fresh Hop Keller Couch Lager",
    "region": "Oregon",
    "style": "Helles"
  },
  {
    "id": 12,
    "brewery": "Burnside Brewing Co",
    "name": "Blueberry Pie",
    "region": "Oregon",
    "style": "Cream Ale w. Blueberry Jam"
  },
  {
    "id": 13,
    "brewery": "Cascade Brewing Company",
    "name": "Pumpkin Smash '15",
    "region": "Oregon",
    "style": "Northwest Sour Ale"
  },
  {
    "id": 14,
    "brewery": "Cascade Brewing Company",
    "name": "Cranberry '16",
    "region": "Oregon",
    "style": "Northwest Sour Ale"
  },
  {
    "id": 15,
    "brewery": "Cascade Brewing Company",
    "name": "Sang Royal '13",
    "region": "Oregon",
    "style": "Northwest Sour Ale"
  },
  {
    "id": 16,
    "brewery": "Cascade Brewing Company",
    "name": "Oblique Irish Breakfast",
    "region": "Oregon",
    "style": "Wood-Aged Coffee Blond Ale"
  },
  {
    "id": 17,
    "brewery": "Commons Brewery",
    "name": "Dark Mild",
    "region": "Oregon",
    "style": "English Mild"
  },
  {
    "id": 18,
    "brewery": "Commons Brewery",
    "name": "Earl Grey Dark Mild",
    "region": "Oregon",
    "style": "English Mild w. Earl Grey"
  },
  {
    "id": 19,
    "brewery": "Commons Brewery",
    "name": "KellerVienne",
    "region": "Oregon",
    "style": "Kellerbier"
  },
  {
    "id": 20,
    "brewery": "Deschutes Brewery",
    "name": "Fresh Hop Fresh Squeezed",
    "region": "Oregon",
    "style": "American IPA"
  },
  {
    "id": 21,
    "brewery": "Deschutes Brewery",
    "name": "Mirror Pond Pale Ale",
    "region": "Oregon",
    "style": "American Pale Ale"
  },
  {
    "id": 22,
    "brewery": "Double Mountain Brewery",
    "name": "Killer Green",
    "region": "Oregon",
    "style": "Fresh Hop IPA"
  },
  {
    "id": 23,
    "brewery": "Double Mountain Brewery",
    "name": "Killer Randall",
    "region": "Oregon",
    "style": "Fresh Hop IPA"
  },
  {
    "id": 24,
    "brewery": "Ecliptic Brewing",
    "name": "Capella Porter",
    "region": "Oregon",
    "style": "Brown Porter"
  },
  {
    "id": 25,
    "brewery": "Ecliptic Brewing",
    "name": "Orbiter IPA",
    "region": "Oregon",
    "style": "American IPA"
  },
  {
    "id": 26,
    "brewery": "Ecliptic Brewing",
    "name": "Quasar Pale Ale",
    "region": "Oregon",
    "style": "American Pale Ale"
  },
  {
    "id": 27,
    "brewery": "Ex Novo Brewing Co.",
    "name": "Elliot IPA",
    "region": "Oregon",
    "style": "American IPA"
  },
  {
    "id": 28,
    "brewery": "Ex Novo Brewing Co.",
    "name": "Browntown Abbey",
    "region": "Oregon",
    "style": "English Brown"
  },
  {
    "id": 29,
    "brewery": "Fat Heads",
    "name": "Built for Speed IPA",
    "region": "Oregon",
    "style": "American IPA"
  },
  {
    "id": 30,
    "brewery": "Fat Heads",
    "name": "Belgian Chocolate Stout",
    "region": "Oregon",
    "style": "Stout w. Raspberries"
  },
  {
    "id": 31,
    "brewery": "Fort George Brewery",
    "name": "Drunkin Pumpkin",
    "region": "Oregon",
    "style": "Amber Ale"
  },
  {
    "id": 32,
    "brewery": "Fort George Brewery",
    "name": "Cavatica Stout",
    "region": "Oregon",
    "style": "American Stout"
  },
  {
    "id": 33,
    "brewery": "Gigantic Brewing",
    "name": "Gigantic IPA",
    "region": "Oregon",
    "style": "American IPA Dry Hopped w. Citra & Simcoe Hops"
  },
  {
    "id": 34,
    "brewery": "Gigantic Brewing",
    "name": "Gigantic IPA",
    "region": "Oregon",
    "style": "American IPA Dry Hopped w. South African Hops"
  },
  {
    "id": 35,
    "brewery": "Gigantic Brewing",
    "name": "Ginormous",
    "region": "Oregon",
    "style": "Imperial IPA"
  },
  {
    "id": 36,
    "brewery": "Gigantic Brewing",
    "name": "Scrilla Pale Ale",
    "region": "Oregon",
    "style": "American Pale Ale"
  },
  {
    "id": 37,
    "brewery": "Gigantic Brewing",
    "name": "High Voltage Winter IPA",
    "region": "Oregon",
    "style": "American IPA"
  },
  {
    "id": 38,
    "brewery": "Gigantic Brewing",
    "name": "Sodbusted Fresh Hop Simcoe IV: The Goblet of Simcoe",
    "region": "Oregon",
    "style": "Fresh Hop Pale Ale"
  },
  {
    "id": 39,
    "brewery": "Gigantic Brewing",
    "name": "Shazoo Imperial Milk Stout",
    "region": "Oregon",
    "style": "Imperial Milk Stout"
  },
  {
    "id": 40,
    "brewery": "Gigantic Brewing",
    "name": "Shazoo Imperial Milk Stout w. Toasted Coconut & Cold Brewed Coava Coffee",
    "region": "Oregon",
    "style": "Imperial Milk Stout"
  },
  {
    "id": 41,
    "brewery": "Hair of the Dog",
    "name": "Doggie Claws",
    "region": "Oregon",
    "style": "Barley Wine"
  },
  {
    "id": 42,
    "brewery": "Hair of the Dog",
    "name": "Adam",
    "region": "Oregon",
    "style": "Old Ale"
  },
  {
    "id": 43,
    "brewery": "Hopworks Urban Brewery",
    "name": "Abominable Winter Ale",
    "region": "Oregon",
    "style": "Strong Red Ale"
  },
  {
    "id": 44,
    "brewery": "Hopworks Urban Brewery",
    "name": "Ace of Spades",
    "region": "Oregon",
    "style": "Double IPA"
  },
  {
    "id": 45,
    "brewery": "Laurelwood Brewery",
    "name": "Laurelwood Pumpkin Ale",
    "region": "Oregon",
    "style": "Pumpkin Ale"
  },
  {
    "id": 46,
    "brewery": "Laurelwood Brewery",
    "name": "Hingle McCringleberry",
    "region": "Oregon",
    "style": "Pale Ale"
  },
  {
    "id": 47,
    "brewery": "Pelican Brewing Company",
    "name": "Pekko IPA",
    "region": "Oregon",
    "style": "American IPA w. Pekko Hops"
  },
  {
    "id": 48,
    "brewery": "Pelican Brewing Company",
    "name": "Doryman's Ale",
    "region": "Oregon",
    "style": "American Brown Ale"
  },
  {
    "id": 49,
    "brewery": "Upright Brewing",
    "name": "Saison Vert",
    "region": "Oregon",
    "style": "Saison"
  },
  {
    "id": 50,
    "brewery": "Beachwood Brewing & BBQ",
    "name": "Melrose Imperiale",
    "region": "California",
    "style": "Imperial IPA"
  },
  {
    "id": 51,
    "brewery": "El Segundo Brewing Co.",
    "name": "White Dog IPA",
    "region": "California",
    "style": "American IPA"
  },
  {
    "id": 52,
    "brewery": "El Segundo Brewing Co.",
    "name": "White Dog IPA",
    "region": "California",
    "style": "American IPA w. Apricots"
  },
  {
    "id": 53,
    "brewery": "Golden Road Brewing",
    "name": "The Way Of The Light",
    "region": "California",
    "style": "American IPA w. Hallertau Blanc Hops"
  },
  {
    "id": 54,
    "brewery": "Golden Road Brewing",
    "name": "Point The Way",
    "region": "California",
    "style": "American IPA w. Guava"
  },
  {
    "id": 55,
    "brewery": "King Harbor Brewing Co.",
    "name": "Hawaiian Swirly",
    "region": "California",
    "style": "American Brown Ale"
  },
  {
    "id": 56,
    "brewery": "King Harbor Brewing Co.",
    "name": "Coconut IPA",
    "region": "California",
    "style": "American IPA w. Coconut"
  },
  {
    "id": 57,
    "brewery": "Ladyface Ale Companie",
    "name": "Coquine",
    "region": "California",
    "style": "Chardonnay Barrel-Aged Belgian Tripel w. Brett."
  },
  {
    "id": 58,
    "brewery": "Ladyface Ale Companie",
    "name": "Ladyface Weizenbock w. Rum Soaked Oak Chips & Nutmeg",
    "region": "California",
    "style": "Weizenbock"
  },
  {
    "id": 59,
    "brewery": "MacLeod Ale Brewing Co.",
    "name": "1918 IPA",
    "region": "California",
    "style": "Traditional English IPA"
  },
  {
    "id": 60,
    "brewery": "MacLeod Ale Brewing Co.",
    "name": "The Black Bear",
    "region": "California",
    "style": "Traditional Porter"
  },
  {
    "id": 61,
    "brewery": "Mikkeller Brewing San Diego",
    "name": "Spells",
    "region": "California",
    "style": "Double IPA w. Mango & Jalapeño"
  },
  {
    "id": 62,
    "brewery": "Mikkeller Brewing San Diego",
    "name": "Br& New Normal",
    "region": "California",
    "style": "Berliner Weisse w. Peaches, Vanilla, & Cinnamon"
  },
  {
    "id": 63,
    "brewery": "Modern Times",
    "name": "Orderville",
    "region": "California",
    "style": "American IPA w. Southern Passion Hops"
  },
  {
    "id": 64,
    "brewery": "Modern Times",
    "name": "MegaBlackHouse",
    "region": "California",
    "style": "Coffee Imperial Stout"
  },
  {
    "id": 65,
    "brewery": "Modern Times",
    "name": "Sleepless City",
    "region": "California",
    "style": "Brown Ale w. Coffee"
  },
  {
    "id": 66,
    "brewery": "Pizza Port Brewing Co.",
    "name": "Graveyards Pale Ale",
    "region": "California",
    "style": "American Pale Ale"
  },
  {
    "id": 67,
    "brewery": "Pizza Port Brewing Co.",
    "name": "Ranchero",
    "region": "California",
    "style": "American IPA"
  },
  {
    "id": 68,
    "brewery": "Sierra Nevada Brewing Co.",
    "name": "Pale Ale",
    "region": "California",
    "style": "American Pale Ale"
  },
  {
    "id": 69,
    "brewery": "Sierra Nevada Brewing Co.",
    "name": "Torpedo Extra IPA",
    "region": "California",
    "style": "American IPA"
  },
  {
    "id": 70,
    "brewery": "Sierra Nevada Brewing Co.",
    "name": "Northern Hemisphere",
    "region": "California",
    "style": "Harvest Wet Hop Ale"
  },
  {
    "id": 71,
    "brewery": "Sierra Nevada Brewing Co.",
    "name": "Narwhal",
    "region": "California",
    "style": "Russian Imperial Stout"
  },
  {
    "id": 72,
    "brewery": "Smog City Brewing",
    "name": "Bloody Knuckle",
    "region": "California",
    "style": "Robust Porter"
  },
  {
    "id": 73,
    "brewery": "Smog City Brewing",
    "name": "Sabre-Toothed Squirrel",
    "region": "California",
    "style": "Hoppy American Amber"
  },
  {
    "id": 74,
    "brewery": "Stone Brewing Co.",
    "name": "Coffee Milk Stout",
    "region": "California",
    "style": "Milk Stout"
  },
  {
    "id": 75,
    "brewery": "Stone Brewing Co.",
    "name": "Ruination 2.0",
    "region": "California",
    "style": "Double IPA"
  },
  {
    "id": 76,
    "brewery": "Stone Brewing Co.",
    "name": "Stone IPA",
    "region": "California",
    "style": "West Coast IPA"
  },
  {
    "id": 77,
    "brewery": "Stone Brewing Co.",
    "name": "Go-To",
    "region": "California",
    "style": "American IPA w. Ginger, Lemon Drop Hops, & Lemon Peel"
  },
  {
    "id": 78,
    "brewery": "12 Gates Brewing Company",
    "name": "Chocolate Peanut Butter Stout",
    "region": "New York",
    "style": "American Double Stout"
  },
  {
    "id": 79,
    "brewery": "12 Gates Brewing Company",
    "name": "French Oak Apricot Pale Ale",
    "region": "New York",
    "style": "American Pale Ale"
  },
  {
    "id": 80,
    "brewery": "42 North Brewing Company",
    "name": "Wallonia Wit",
    "region": "New York",
    "style": "Belgian style Wit"
  },
  {
    "id": 81,
    "brewery": "Barrier Brewing Co.",
    "name": "Money IPA",
    "region": "New York",
    "style": "American IPA w. Whole Leaf Simcoe Hops"
  },
  {
    "id": 82,
    "brewery": "Barrier Brewing Co.",
    "name": "Impostor",
    "region": "New York",
    "style": "Czech Pilsner w. Hallertau Hops"
  },
  {
    "id": 83,
    "brewery": "Barrier Brewing Co.",
    "name": "Boons Brew: Thai Bird Chilies",
    "region": "New York",
    "style": "American Pale Dry w. Citra Hops"
  },
  {
    "id": 84,
    "brewery": "Barrier Brewing Co.",
    "name": "Earth",
    "region": "New York",
    "style": "Brown Ale w. Ethiopian Yirgacheffe"
  },
  {
    "id": 85,
    "brewery": "Barrier Brewing Co.",
    "name": "Dunegrass",
    "region": "New York",
    "style": "Double IPA w. Centennial Hops"
  },
  {
    "id": 86,
    "brewery": "Captain Lawrence Brewing Company",
    "name": "Palate Shifter",
    "region": "New York",
    "style": "Imperial IPA w. Motueka & Green Bullet Hops"
  },
  {
    "id": 87,
    "brewery": "Captain Lawrence Brewing Company",
    "name": "Sour Commute",
    "region": "New York",
    "style": "Sour IPA w. Columbus, Mosaic, Motueka & Citra Hops"
  },
  {
    "id": 88,
    "brewery": "Community Beer Works",
    "name": "THE Double IPA",
    "region": "New York",
    "style": "Imperial IPA"
  },
  {
    "id": 89,
    "brewery": "Community Beer Works",
    "name": "Heatrays",
    "region": "New York",
    "style": "Barleywine"
  },
  {
    "id": 90,
    "brewery": "Flying Bison Brewing Company",
    "name": "Dry Hopped Aviator Red",
    "region": "New York",
    "style": "Irish Red Ale 90"
  },
  {
    "id": 91,
    "brewery": "Flying Bison Brewing Company",
    "name": "2015 Spot Coffee Stout w. Cocoa Nibs",
    "region": "New York",
    "style": "Imperial Oatmeal Coffee Stout"
  },
  {
    "id": 92,
    "brewery": "Hamburg Brewing Company",
    "name": "Irish Red Ale",
    "region": "New York",
    "style": "Irish Style Red Ale"
  },
  {
    "id": 93,
    "brewery": "Hamburg Brewing Company",
    "name": "Hoppenstance",
    "region": "New York",
    "style": "American Double India Pale Ale"
  },
  {
    "id": 94,
    "brewery": "Middle Ages Brewing",
    "name": "Single Batch IPA #7",
    "region": "New York",
    "style": "India Pale Ale"
  },
  {
    "id": 95,
    "brewery": "Middle Ages Brewing",
    "name": "Syracuse Pale Ale",
    "region": "New York",
    "style": "Golden Ale Age On Toasted French Oak Spirals"
  },
  {
    "id": 96,
    "brewery": "New York Beer Project",
    "name": "Borough Brown",
    "region": "New York",
    "style": "American Brown Ale with Chipotle Peppers & Cacao Nibs"
  },
  {
    "id": 97,
    "brewery": "Pearl Street Grill & Brewery",
    "name": "Trainwreck Amber Ale",
    "region": "New York",
    "style": "Amber Ale"
  },
  {
    "id": 98,
    "brewery": "Resurgence Brewing Company",
    "name": "Imperial Irish Breakfast",
    "region": "New York",
    "style": "Smoked Irish Red w. Maple"
  },
  {
    "id": 99,
    "brewery": "SingleCut Beersmiths",
    "name": "Full Stock",
    "region": "New York",
    "style": "Double IPA"
  },
  {
    "id": 100,
    "brewery": "SingleCut Beersmiths",
    "name": "Forty Things We Share",
    "region": "New York",
    "style": "Double IPA"
  },
  {
    "id": 101,
    "brewery": "Stoneyard Brewing Company",
    "name": "Cherry Lime Sour",
    "region": "New York",
    "style": "Fruited Sour"
  },
  {
    "id": 102,
    "brewery": "Stoneyard Brewing Company",
    "name": "Rye-it Porter",
    "region": "New York",
    "style": "Robust Rye Porter w. Amaretto & Toasted Coconut"
  },
  {
    "id": 103,
    "brewery": "Thin Man Brewery",
    "name": "No Pressure",
    "region": "New York",
    "style": "American IPA"
  },
  {
    "id": 104,
    "brewery": "Thin Man Brewery",
    "name": "Dummy",
    "region": "New York",
    "style": "Belgian Pale Ale"
  },
  {
    "id": 105,
    "brewery": "Bad Apple",
    "name": "Black & Tackle",
    "region": "Maritimes",
    "style": "Russian Imperial Stout"
  },
  {
    "id": 106,
    "brewery": "Bad Apple",
    "name": "Mosaic",
    "region": "Maritimes",
    "style": "Double IPA"
  },
  {
    "id": 107,
    "brewery": "Big Spruce",
    "name": "Bitter Get'er India",
    "region": "Maritimes",
    "style": "Organic Black IPA"
  },
  {
    "id": 108,
    "brewery": "Big Spruce",
    "name": "Craig Goes Yard",
    "region": "Maritimes",
    "style": "Organic Wet Hopped Harvest IPA"
  },
  {
    "id": 109,
    "brewery": "Big Spruce",
    "name": "Cereal Killer",
    "region": "Maritimes",
    "style": "Oatmeal Stout"
  },
  {
    "id": 110,
    "brewery": "Boxing Rock",
    "name": "Hunky Dory Pale Ale w. Ginger",
    "region": "Maritimes",
    "style": "Pale Ale"
  },
  {
    "id": 111,
    "brewery": "Boxing Rock",
    "name": "Crafty Jack English Ale",
    "region": "Maritimes",
    "style": "English Ale"
  },
  {
    "id": 112,
    "brewery": "Garrison",
    "name": "Wet & Dry IPA",
    "region": "Maritimes",
    "style": "American IPA"
  },
  {
    "id": 113,
    "brewery": "Garrison",
    "name": "Juicy Fruit",
    "region": "Maritimes",
    "style": "Double IPA"
  },
  {
    "id": 114,
    "brewery": "Garrison",
    "name": "Peanut Butter & Honey",
    "region": "Maritimes",
    "style": "Brown Ale"
  },
  {
    "id": 115,
    "brewery": "PEI Brewing Company",
    "name": "Brett on the Beach",
    "region": "Maritimes",
    "style": "Barrel Aged Saison w.Brett"
  },
  {
    "id": 116,
    "brewery": "PEI Brewing Company",
    "name": "The Farmer's Daughter",
    "region": "Maritimes",
    "style": "Dry Hopped Brett Saison w. Apricots"
  },
  {
    "id": 117,
    "brewery": "Pumphouse",
    "name": "Pumphouse Oktoberfest",
    "region": "Maritimes",
    "style": "Oktoberfest"
  },
  {
    "id": 118,
    "brewery": "Spindrift",
    "name": "Abyss",
    "region": "Maritimes",
    "style": "Schwarzbier"
  },
  {
    "id": 119,
    "brewery": "Spindrift",
    "name": "Kenobier",
    "region": "Maritimes",
    "style": "Munich Helles w. Mandarina Bavaria Hops"
  },
  {
    "id": 120,
    "brewery": "Spindrift",
    "name": "Knotty Buoy 2.0",
    "region": "Maritimes",
    "style": "Kellerpils w. Herkules & Huell Melon Hops"
  },
  {
    "id": 121,
    "brewery": "Tatamagouche",
    "name": "Cellar Slammer",
    "region": "Maritimes",
    "style": "India Session Ale"
  },
  {
    "id": 122,
    "brewery": "Tatamagouche",
    "name": "BaTATAry Park",
    "region": "Maritimes",
    "style": "West Coast Pale Ale"
  },
  {
    "id": 123,
    "brewery": "Unflitered",
    "name": "Mosaic SMaSH",
    "region": "Maritimes",
    "style": "Double IPA"
  },
  {
    "id": 124,
    "brewery": "Unflitered",
    "name": "Flat Black Jesus",
    "region": "Maritimes",
    "style": "American Stout"
  },
  {
    "id": 125,
    "brewery": "Upstreet",
    "name": "Pretty Sweet Life",
    "region": "Maritimes",
    "style": "Imperial Pumpkin Spice Latte Ale"
  },
  {
    "id": 126,
    "brewery": "Parallel 49 Brewing",
    "name": "Vow of Silence",
    "region": "British Columbia",
    "style": "Belgian Strong Ale"
  },
  {
    "id": 127,
    "brewery": "Parallel 49 Brewing",
    "name": "Don't Razz Me About The Gypsy",
    "region": "British Columbia",
    "style": "Red Ale w. Raspberries & Cinnamon"
  },
  {
    "id": 128,
    "brewery": "Parallel 49 Brewing",
    "name": "Filthy Fruit Madness",
    "region": "British Columbia",
    "style": "American IPA"
  },
  {
    "id": 129,
    "brewery": "Parallel 49 Brewing",
    "name": "The Detox",
    "region": "British Columbia",
    "style": "Ruby Ale w. Hallertau Blanc Hops"
  },
  {
    "id": 130,
    "brewery": "Parallel 49 Brewing",
    "name": "Hangover Killer",
    "region": "British Columbia",
    "style": "Ruby Ale w. Orange & Cinnamon"
  },
  {
    "id": 131,
    "brewery": "Bridge",
    "name": "Bourbon Blood Orange",
    "region": "British Columbia",
    "style": "Oaked Wheat Ale w. Blood Orange & Bourbon"
  },
  {
    "id": 132,
    "brewery": "Central City",
    "name": "Central City Sour III",
    "region": "British Columbia",
    "style": "Farmhouse Ale w. Raspberries"
  },
  {
    "id": 133,
    "brewery": "Central City",
    "name": "Red Racer X Parkside Brewery Central Park",
    "region": "British Columbia",
    "style": "Fresh Hopped XPA"
  },
  {
    "id": 134,
    "brewery": "Driftwood",
    "name": "Blackstone",
    "region": "British Columbia",
    "style": "London Dry Porter"
  },
  {
    "id": 135,
    "brewery": "Four Winds",
    "name": "Nectarous",
    "region": "British Columbia",
    "style": "Dry Hopped Sour"
  },
  {
    "id": 136,
    "brewery": "Four Winds",
    "name": "Juxtapose",
    "region": "British Columbia",
    "style": "Wild IPA w. Mango & Habanero"
  },
  {
    "id": 137,
    "brewery": "Four Winds",
    "name": "Pequeno Cabo",
    "region": "British Columbia",
    "style": "Tequilla Barrel Aged Berliner Weisse"
  },
  {
    "id": 138,
    "brewery": "Four Winds",
    "name": "Vexillum",
    "region": "British Columbia",
    "style": "Imperial IPA"
  },
  {
    "id": 139,
    "brewery": "Four Winds",
    "name": "Featherweight IPA",
    "region": "British Columbia",
    "style": "Session IPA"
  },
  {
    "id": 140,
    "brewery": "Howe Sound",
    "name": "Sky Pilot",
    "region": "British Columbia",
    "style": "North West Pale Ale"
  },
  {
    "id": 141,
    "brewery": "Howe Sound",
    "name": "Wee Beastie",
    "region": "British Columbia",
    "style": "Oak Aged Wee Heavy Scotch Ale"
  },
  {
    "id": 142,
    "brewery": "Howe Sound",
    "name": "Baltic Porter w. Red Grape Must & Sour Plums",
    "region": "British Columbia",
    "style": "Baltic Porter"
  },
  {
    "id": 143,
    "brewery": "Howe Sound",
    "name": "Pumpkineater",
    "region": "British Columbia",
    "style": "Rum & Chocolate Aged Pumpkin Ale"
  },
  {
    "id": 144,
    "brewery": "Howe Sound",
    "name": "Equinox",
    "region": "British Columbia",
    "style": "Rye Oak Aged IPA"
  },
  {
    "id": 145,
    "brewery": "Howe Sound",
    "name": "Dubbel",
    "region": "British Columbia",
    "style": "Belgian Style Dubbel w. Cold Brew Coffee"
  },
  {
    "id": 146,
    "brewery": "Howe Sound",
    "name": "Megadestroyer",
    "region": "British Columbia",
    "style": "Imperial Licorice Stout"
  },
  {
    "id": 147,
    "brewery": "Howe Sound",
    "name": "Devil's Elbow IPA",
    "region": "British Columbia",
    "style": "Dry Hopped English IPA"
  },
  {
    "id": 148,
    "brewery": "Moody Ales",
    "name": "Raspberry Lime IPA",
    "region": "British Columbia",
    "style": "American IPA w. Raspberries & Lime"
  },
  {
    "id": 149,
    "brewery": "Moody Ales",
    "name": "Mango Pale Ale",
    "region": "British Columbia",
    "style": "American Pale Ale w. Mango"
  },
  {
    "id": 150,
    "brewery": "Steel & Oak",
    "name": "ESB w. Cascade",
    "region": "British Columbia",
    "style": "Galaxy, Simcoe & Mandarina Bavaria Hops, Extra Special Bitter"
  },
  {
    "id": 151,
    "brewery": "Steel Toad",
    "name": "Yorkshire Best Bitter",
    "region": "British Columbia",
    "style": "Best Bitter"
  },
  {
    "id": 152,
    "brewery": "Steel Toad",
    "name": "Dry Hopped Sour",
    "region": "British Columbia",
    "style": "Dry Hopped Berliner Weisse"
  },
  {
    "id": 153,
    "brewery": "Steel Toad",
    "name": "Raspberry Sour",
    "region": "British Columbia",
    "style": "Fruit Berliner Weisse"
  },
  {
    "id": 154,
    "brewery": "Yellow Dog",
    "name": "Pineapple Play Dead",
    "region": "British Columbia",
    "style": "American IPA"
  },
  {
    "id": 155,
    "brewery": "A La Fut",
    "name": "Assemblage de LambiQcs",
    "region": "Quebec",
    "style": "Wild Fermented Barrel-Aged Sour Ale"
  },
  {
    "id": 156,
    "brewery": "Benelux",
    "name": "Gloriosa",
    "region": "Quebec",
    "style": "White IPA"
  },
  {
    "id": 157,
    "brewery": "Benelux",
    "name": "Mascarade",
    "region": "Quebec",
    "style": "American IPA"
  },
  {
    "id": 158,
    "brewery": "Benelux",
    "name": "Buzz",
    "region": "Quebec",
    "style": "American IPA"
  },
  {
    "id": 159,
    "brewery": "Benelux",
    "name": "San Lupulo",
    "region": "Quebec",
    "style": "American Pale Ale"
  },
  {
    "id": 160,
    "brewery": "Brasserie Dunham",
    "name": "Tropicale IPA",
    "region": "Quebec",
    "style": "Farmhouse IPA"
  },
  {
    "id": 161,
    "brewery": "Brasserie Dunham",
    "name": "Oro Zuur",
    "region": "Quebec",
    "style": "Dry Hopped Golden Sour Ale"
  },
  {
    "id": 162,
    "brewery": "Brasserie Dunham",
    "name": "Coco Chipotle Porter",
    "region": "Quebec",
    "style": "Bourbon Barrel-Aged Robust Porter"
  },
  {
    "id": 163,
    "brewery": "Brasserie Dunham",
    "name": "Saison Fleurs Sauvages ''Ete''",
    "region": "Quebec",
    "style": "Wildflower Saison"
  },
  {
    "id": 164,
    "brewery": "Brassuers Du Monde",
    "name": "Saison Balsam Fir",
    "region": "Quebec",
    "style": "Saison"
  },
  {
    "id": 165,
    "brewery": "Brassuers Du Monde",
    "name": "Gose Mozaik",
    "region": "Quebec",
    "style": "German Sour Wheat"
  },
  {
    "id": 166,
    "brewery": "Brassuers Du Monde",
    "name": "SMASH Simco Tamarin",
    "region": "Quebec",
    "style": "American Pale Ale"
  },
  {
    "id": 167,
    "brewery": "Brassuers Du Monde",
    "name": "Interdite",
    "region": "Quebec",
    "style": "American Pale Ale w. Kiwi & Juniper"
  },
  {
    "id": 168,
    "brewery": "Brassuers Du Monde",
    "name": "Big Ben",
    "region": "Quebec",
    "style": "Porter w. Coffee"
  },
  {
    "id": 169,
    "brewery": "Dieu Du Ciel!",
    "name": "Chez Suzanne Rhubarb",
    "region": "Quebec",
    "style": "Stout w. Rhubarb"
  },
  {
    "id": 170,
    "brewery": "Dieu Du Ciel!",
    "name": "Sul' Pouce Vers La Galaxie",
    "region": "Quebec",
    "style": "American IPA w. Galaxy Hops"
  },
  {
    "id": 171,
    "brewery": "Dieu Du Ciel!",
    "name": "Tete de Corbeau Denali Hop",
    "region": "Quebec",
    "style": "American Pale Ale"
  },
  {
    "id": 172,
    "brewery": "Dieu Du Ciel!",
    "name": "Alban Elved",
    "region": "Quebec",
    "style": "Harvest Ale w. Quebec Hops"
  },
  {
    "id": 173,
    "brewery": "Dieu Du Ciel!",
    "name": "Vaisseau des Songes",
    "region": "Quebec",
    "style": "American IPA w. Golding Hops"
  },
  {
    "id": 174,
    "brewery": "Dieu Du Ciel!",
    "name": "Resurrection",
    "region": "Quebec",
    "style": "Porter w. Bourbon Soaked Oak Chips"
  },
  {
    "id": 175,
    "brewery": "Dieu Du Ciel!",
    "name": "Castelnau",
    "region": "Quebec",
    "style": "Brown Ale w. Golding Hops"
  },
  {
    "id": 176,
    "brewery": "Dieu Du Ciel!",
    "name": "Ultra Mosaika",
    "region": "Quebec",
    "style": "American Pale Ale w. Mosaic Hops"
  },
  {
    "id": 177,
    "brewery": "Hopera",
    "name": "Trizo Prune",
    "region": "Quebec",
    "style": "Tripel w. Fresh Plums"
  },
  {
    "id": 178,
    "brewery": "Hopera",
    "name": "Strawberry Wine MCV Basilic",
    "region": "Quebec",
    "style": "Barleywine w. Strawberries"
  },
  {
    "id": 179,
    "brewery": "Hopera",
    "name": "IS Radical L’erudit Cafe-Vanille",
    "region": "Quebec",
    "style": "Imperial Stout w. Coffee"
  },
  {
    "id": 180,
    "brewery": "Hopfenstark",
    "name": "Postcolonial IPA",
    "region": "Quebec",
    "style": "Amercian IPA"
  },
  {
    "id": 181,
    "brewery": "Hopfenstark",
    "name": "End of the Trail",
    "region": "Quebec",
    "style": "American Pale Ale"
  },
  {
    "id": 182,
    "brewery": "Isle De Garde",
    "name": "IPA Resineuse",
    "region": "Quebec",
    "style": "Resinous IPA"
  },
  {
    "id": 183,
    "brewery": "Isle De Garde",
    "name": "Pale Ale Americaine",
    "region": "Quebec",
    "style": "American Pale Ale"
  },
  {
    "id": 184,
    "brewery": "La Succursale",
    "name": "1814 Coconut & Vanilla Porter",
    "region": "Quebec",
    "style": "Porter"
  },
  {
    "id": 185,
    "brewery": "La Succursale",
    "name": "Assemblage Cafe",
    "region": "Quebec",
    "style": "Berliner Weiss & Porter Blend w. Coffee"
  },
  {
    "id": 186,
    "brewery": "Le Castor",
    "name": "Yakima IPA",
    "region": "Quebec",
    "style": "American IPA"
  },
  {
    "id": 187,
    "brewery": "Le Castor",
    "name": "Session Houblon",
    "region": "Quebec",
    "style": "Session IPA"
  },
  {
    "id": 188,
    "brewery": "Le Castor",
    "name": "Oatmeal Stout",
    "region": "Quebec",
    "style": "Oatmeal Stout"
  },
  {
    "id": 189,
    "brewery": "Le Trefle Noir",
    "name": "California",
    "region": "Quebec",
    "style": "American IPA w. Citra, Lemon & Grapefruit"
  },
  {
    "id": 190,
    "brewery": "Le Trefle Noir",
    "name": "Trefle Noir",
    "region": "Quebec",
    "style": "Oatmeal Stout w. Vanilla & Chai Tea"
  },
  {
    "id": 191,
    "brewery": "Le Trou Du Diable",
    "name": "Dulcis Succubus",
    "region": "Quebec",
    "style": "Barrel Aged Saison"
  },
  {
    "id": 192,
    "brewery": "Le Trou Du Diable",
    "name": "L'Imperatrice",
    "region": "Quebec",
    "style": "Bourbon Barrel Aged Imperial Stout"
  },
  {
    "id": 193,
    "brewery": "Le Trou Du Diable",
    "name": "L'Ours",
    "region": "Quebec",
    "style": "Blend of Young & Sour Saisons"
  },
  {
    "id": 194,
    "brewery": "Le Trou Du Diable",
    "name": "Le Coq",
    "region": "Quebec",
    "style": "Sour Saison w. Cherries"
  },
  {
    "id": 195,
    "brewery": "Le Trou Du Diable",
    "name": "La Buteuse",
    "region": "Quebec",
    "style": "Barrel Aged Belgian Tripel"
  },
  {
    "id": 196,
    "brewery": "Le Trou Du Diable",
    "name": "La Willow Gose w. Raspberries",
    "region": "Quebec",
    "style": "Gose"
  },
  {
    "id": 197,
    "brewery": "Les Trois Mousquetaires",
    "name": "Saison Osmanthus",
    "region": "Quebec",
    "style": "Saison w. Osmanthus Flowers"
  },
  {
    "id": 198,
    "brewery": "Les Trois Mousquetaires",
    "name": "Wasabi Denial",
    "region": "Quebec",
    "style": "Sour Ale w. Wasabi"
  },
  {
    "id": 199,
    "brewery": "Les Trois Mousquetaires",
    "name": "Brett Me Up",
    "region": "Quebec",
    "style": "Scotty!, Scotch Barrel-Aged Dark Ale w. Brett"
  },
  {
    "id": 200,
    "brewery": "Les Trois Mousquetaires",
    "name": "Worchestershire Mild Ale",
    "region": "Quebec",
    "style": "English Mild w. Worchestershire Sauce"
  },
  {
    "id": 201,
    "brewery": "Les Trois Mousquetaires",
    "name": "Shitake Brown Ale",
    "region": "Quebec",
    "style": "Brown Ale w. Shitake Mushrooms"
  },
  {
    "id": 202,
    "brewery": "Les Trois Mousquetaires",
    "name": "Porter Baltique Special Edition 2015",
    "region": "Quebec",
    "style": "Aged in Brandy & Bourbon Barrels"
  },
  {
    "id": 203,
    "brewery": "Macallen Farm & Brewery",
    "name": "Repit Du Fermier",
    "region": "Quebec",
    "style": "English Country Side Ale"
  },
  {
    "id": 204,
    "brewery": "Macallen Farm & Brewery",
    "name": "Belier Noire",
    "region": "Quebec",
    "style": "Double Porter"
  },
  {
    "id": 205,
    "brewery": "Macallen Farm & Brewery",
    "name": "Recession a la Ferme",
    "region": "Quebec",
    "style": "Rye Session IPA"
  },
  {
    "id": 206,
    "brewery": "Macallen Farm & Brewery",
    "name": "Kildare",
    "region": "Quebec",
    "style": "Paysanne Pilsner"
  },
  {
    "id": 207,
    "brewery": "Micro Brasserie La Memphre",
    "name": "1908",
    "region": "Quebec",
    "style": "Milk Stout w. Liquorice Wood, Coffee & Columbus Hops"
  },
  {
    "id": 208,
    "brewery": "Micro Brasserie La Memphre",
    "name": "Atley",
    "region": "Quebec",
    "style": "American Pale Ale"
  },
  {
    "id": 209,
    "brewery": "3 Brewers",
    "name": "Little Tipuna",
    "region": "Ontario",
    "style": "Wheat Ale"
  },
  {
    "id": 210,
    "brewery": "3 Brewers",
    "name": "Juicy Pink Stuff",
    "region": "Ontario",
    "style": "American IPA"
  },
  {
    "id": 211,
    "brewery": "3 Brewers",
    "name": "I'se the B'y",
    "region": "Ontario",
    "style": "Saison & Gose Hybrid"
  },
  {
    "id": 212,
    "brewery": "Amsterdam Brewery",
    "name": "El Jaguar",
    "region": "Ontario",
    "style": "Barrel Aged Double Tempest w. Chocolate & Chilies"
  },
  {
    "id": 213,
    "brewery": "Amsterdam Brewery",
    "name": "18 Dirty Hands",
    "region": "Ontario",
    "style": "Rustic Pale Ale w. Brettanomyces"
  },
  {
    "id": 214,
    "brewery": "Amsterdam Brewery",
    "name": "Brush Fire",
    "region": "Ontario",
    "style": "Smoked Porter"
  },
  {
    "id": 215,
    "brewery": "Amsterdam Brewery X Great Lakes Brewing",
    "name": "Coup de Grace",
    "region": "Ontario",
    "style": "Barrel Aged Double Stout"
  },
  {
    "id": 216,
    "brewery": "B&it Brewery",
    "name": "South Indian Saison",
    "region": "Ontario",
    "style": "Sour Farmhouse Ale"
  },
  {
    "id": 217,
    "brewery": "B&it Brewery",
    "name": "Pepper in the Sky",
    "region": "Ontario",
    "style": "American Porter w. Smoked Malt & Peppercorns"
  },
  {
    "id": 218,
    "brewery": "Barncat Artisan Ales",
    "name": "Durian Saison",
    "region": "Ontario",
    "style": "Fruit Saison, 6.5%"
  },
  {
    "id": 219,
    "brewery": "Barncat Artisan Ales",
    "name": "Cat Deactivator w. Simcoe Hops",
    "region": "Ontario",
    "style": "Barley Wine"
  },
  {
    "id": 220,
    "brewery": "Barnstormer Brewing Co.",
    "name": "Flocking Fokker",
    "region": "Ontario",
    "style": "Oktoberfest"
  },
  {
    "id": 221,
    "brewery": "Barnstormer Brewing Co.",
    "name": "Billy's Bong Water",
    "region": "Ontario",
    "style": "English Brown Ale"
  },
  {
    "id": 222,
    "brewery": "BATCH",
    "name": "Plum Saison",
    "region": "Ontario",
    "style": "Saison w. Plums"
  },
  {
    "id": 223,
    "brewery": "Beau's All Natural Brewing Co.",
    "name": "Farm Table: Märzen",
    "region": "Ontario",
    "style": "Oktoberfest Lager"
  },
  {
    "id": 224,
    "brewery": "Beau's All Natural Brewing Co.",
    "name": "Farm Table: English Bitter",
    "region": "Ontario",
    "style": "British-Style Pale Ale"
  },
  {
    "id": 225,
    "brewery": "Beau's All Natural Brewing Co.",
    "name": "B-Side Brewing Label: Kissmeyer NPA",
    "region": "Ontario",
    "style": "Nordic Pale Ale"
  },
  {
    "id": 226,
    "brewery": "Beau's All Natural Brewing Co.",
    "name": "B-Side Brewing Label: Gigantic La Formidable",
    "region": "Ontario",
    "style": "American Belgo-IPA"
  },
  {
    "id": 227,
    "brewery": "Bellwoods Brewery",
    "name": "Jelly King Mandarina Bavaria",
    "region": "Ontario",
    "style": "Dry Hopped Sour"
  },
  {
    "id": 228,
    "brewery": "Bellwoods Brewery",
    "name": "Jelly King Nelson Sauvin",
    "region": "Ontario",
    "style": "Dry Hopped Sour"
  },
  {
    "id": 229,
    "brewery": "Bellwoods Brewery",
    "name": "Jelly King Galaxy",
    "region": "Ontario",
    "style": "Dry Hopped Sour"
  },
  {
    "id": 230,
    "brewery": "Big Rig Brewery",
    "name": "Salty Stache",
    "region": "Ontario",
    "style": "Gose"
  },
  {
    "id": 231,
    "brewery": "Big Rig Brewery",
    "name": "CH CH Cherry Bomb",
    "region": "Ontario",
    "style": "Cherry Oaked Chocolate Belgian Brown"
  },
  {
    "id": 232,
    "brewery": "Big Rock Brewery",
    "name": "Dan's First Diss-Track",
    "region": "Ontario",
    "style": "Bourbon Barrel Aged Dark Amber"
  },
  {
    "id": 233,
    "brewery": "Big Rock Brewery",
    "name": "The Naked Swordsman",
    "region": "Ontario",
    "style": "Smoked Spruce Tip & Raspberry Ale"
  },
  {
    "id": 234,
    "brewery": "Black Oak Brewery",
    "name": "Sink or Swim",
    "region": "Ontario",
    "style": "Citra Saison"
  },
  {
    "id": 235,
    "brewery": "Black Oak Brewery",
    "name": "Side Piece",
    "region": "Ontario",
    "style": "Brett IPA"
  },
  {
    "id": 236,
    "brewery": "Black Oak Brewery",
    "name": "Nox Aeterna",
    "region": "Ontario",
    "style": "Smoked Stout w. Rhum"
  },
  {
    "id": 237,
    "brewery": "Blood Brothers Brewing",
    "name": "The Swarm",
    "region": "Ontario",
    "style": "Oatmeal Honey Ae"
  },
  {
    "id": 238,
    "brewery": "Blood Brothers Brewing",
    "name": "Skollm",
    "region": "Ontario",
    "style": "Brett Stout"
  },
  {
    "id": 239,
    "brewery": "Blood Brothers Brewing",
    "name": "Torch",
    "region": "Ontario",
    "style": "Brett Double IPA"
  },
  {
    "id": 240,
    "brewery": "Bobcaygeon Brewing Company",
    "name": "Common Loon",
    "region": "Ontario",
    "style": "American Pale Ale w. Motueka & Centennial Hops"
  },
  {
    "id": 241,
    "brewery": "Bobcaygeon Brewing Company",
    "name": "Porter After Nine w. Yirgacheffe Coffee",
    "region": "Ontario",
    "style": "Robust Porter"
  },
  {
    "id": 242,
    "brewery": "Boshkung",
    "name": "It's Not Easy' Ale",
    "region": "Ontario",
    "style": "Wine Barrel Aged Frambroise w. Brett"
  },
  {
    "id": 243,
    "brewery": "Brasserie Etienne Brule",
    "name": "Back Draft",
    "region": "Ontario",
    "style": "Organic Black IPA w. Tart Cherries"
  },
  {
    "id": 244,
    "brewery": "Brasserie Etienne Brule",
    "name": "L'Eternelle",
    "region": "Ontario",
    "style": "Organic Brett Saison w. Cranberries & Raspberries"
  },
  {
    "id": 245,
    "brewery": "Burdock Brewery",
    "name": "Pinot 16",
    "region": "Ontario",
    "style": "Beer-Wine Hybrid"
  },
  {
    "id": 246,
    "brewery": "Burdock Brewery",
    "name": "Chard 16",
    "region": "Ontario",
    "style": "Beer-Wine Hybrid"
  },
  {
    "id": 247,
    "brewery": "Calabogie Brewing",
    "name": "Down Stream",
    "region": "Ontario",
    "style": "Kettle Sour w. Brett & Apricots"
  },
  {
    "id": 248,
    "brewery": "Calabogie Brewing",
    "name": "Brown Cow",
    "region": "Ontario",
    "style": "Bourbon Barrel Aged Stout w. Cacao Nibs"
  },
  {
    "id": 249,
    "brewery": "Calabogie Brewing",
    "name": "Big Black Donald",
    "region": "Ontario",
    "style": "Bourbon Barrel-Aged Imperial Stout w. Madagascar Vanilla Beans"
  },
  {
    "id": 250,
    "brewery": "Cameron's Brewing Company",
    "name": "Crammed w. Hippos",
    "region": "Ontario",
    "style": "American IPA"
  },
  {
    "id": 251,
    "brewery": "Cameron's Brewing Company",
    "name": "Celebrity Sex Tape Vol 2",
    "region": "Ontario",
    "style": "Wild Saison"
  },
  {
    "id": 252,
    "brewery": "Cheshire Valley Brewing Co.",
    "name": "CV-ESB",
    "region": "Ontario",
    "style": "Extra Special Bitter"
  },
  {
    "id": 253,
    "brewery": "Clifford Brewing Co.",
    "name": "Sour Cherry Porter",
    "region": "Ontario",
    "style": "Robust Porter"
  },
  {
    "id": 254,
    "brewery": "Clifford Brewing Co.",
    "name": "Pinball Wizard (Dry Hopped Barrel Aged Blend)",
    "region": "Ontario",
    "style": "American Pale Ale"
  },
  {
    "id": 255,
    "brewery": "Collective Arts Brewing Co.",
    "name": "Stranger Than Fiction",
    "region": "Ontario",
    "style": "Porter"
  },
  {
    "id": 256,
    "brewery": "Collective Arts Brewing Co.",
    "name": "Collective Project: Sour Pumpkin Saison",
    "region": "Ontario",
    "style": "Sour Pumpkin Saison"
  },
  {
    "id": 257,
    "brewery": "Collective Arts Brewing Co.",
    "name": "Rhyme & Reason",
    "region": "Ontario",
    "style": "Extra Pale Ale"
  },
  {
    "id": 258,
    "brewery": "Collective Arts Brewing Co.",
    "name": "State of Mind",
    "region": "Ontario",
    "style": "Session IPA"
  },
  {
    "id": 259,
    "brewery": "County Durham Brewing Company",
    "name": "Mad Cow",
    "region": "Ontario",
    "style": "Milk Stout"
  },
  {
    "id": 260,
    "brewery": "Craft Heads Brewing Company",
    "name": "Large Hoptron Collider",
    "region": "Ontario",
    "style": "Imperial IPA"
  },
  {
    "id": 261,
    "brewery": "Craft Heads Brewing Company",
    "name": "Brett \"The Hibiscus\" Hart",
    "region": "Ontario",
    "style": "Brett Sour"
  },
  {
    "id": 262,
    "brewery": "Elora Brewing",
    "name": "Elora Borealis",
    "region": "Ontario",
    "style": "Pale Ale w. Citra Hops"
  },
  {
    "id": 263,
    "brewery": "Flying Monkeys",
    "name": "Betty White Stout",
    "region": "Ontario",
    "style": "Stout"
  },
  {
    "id": 264,
    "brewery": "Flying Monkeys",
    "name": "Deep Tracks",
    "region": "Ontario",
    "style": "American Brown Ale"
  },
  {
    "id": 265,
    "brewery": "Folly Brewing",
    "name": "ULLA!",
    "region": "Ontario",
    "style": "Dark Farmhouse Ale w. Raspberries"
  },
  {
    "id": 266,
    "brewery": "Forked River Brewing Company",
    "name": "Reforest Kelley",
    "region": "Ontario",
    "style": "Sour Bourbon Barrel Aged Imperial Stout"
  },
  {
    "id": 267,
    "brewery": "Forked River Brewing Company",
    "name": "Talk Brett'y To Me",
    "region": "Ontario",
    "style": "Brett Wheat Ale"
  },
  {
    "id": 268,
    "brewery": "Granite Brewery",
    "name": "Galactic Pale Ale",
    "region": "Ontario",
    "style": "American Pale Ale"
  },
  {
    "id": 269,
    "brewery": "Granite Brewery",
    "name": "Darkside Black IPA",
    "region": "Ontario",
    "style": "American IPA"
  },
  {
    "id": 270,
    "brewery": "Granite Brewery",
    "name": "Pumpkin Jack Flash",
    "region": "Ontario",
    "style": "Pumpkin Ale"
  },
  {
    "id": 271,
    "brewery": "Granite Brewery",
    "name": "1812 Porter",
    "region": "Ontario",
    "style": "Robust Porter"
  },
  {
    "id": 272,
    "brewery": "Great Lakes Brewery",
    "name": "No Chance w. Miranda",
    "region": "Ontario",
    "style": "Brett Saison"
  },
  {
    "id": 273,
    "brewery": "Great Lakes Brewery",
    "name": "Mocha Machine",
    "region": "Ontario",
    "style": "Bourbon Barrel-Aged Coffee & Chocolate Porter"
  },
  {
    "id": 274,
    "brewery": "Great Lakes Brewery",
    "name": "Behind The Wavy Wall",
    "region": "Ontario",
    "style": "Imperial Stout w. Vanilla Bean"
  },
  {
    "id": 275,
    "brewery": "Great Lakes Brewery",
    "name": "Notella",
    "region": "Ontario",
    "style": "Chocolate Hazlenut Stout"
  },
  {
    "id": 276,
    "brewery": "Halo Brewery",
    "name": "Event Horizon",
    "region": "Ontario",
    "style": "Foreign Extra Stout w. Sarsaparilla"
  },
  {
    "id": 277,
    "brewery": "Halo Brewery",
    "name": "Elder God",
    "region": "Ontario",
    "style": "Malt Cider w. Elderberry & Elderflower"
  },
  {
    "id": 278,
    "brewery": "Henderson Brewing Company",
    "name": "Dry Hopped Tart",
    "region": "Ontario",
    "style": "Cherry Berliner Weisse"
  },
  {
    "id": 279,
    "brewery": "Henderson Brewing Company",
    "name": "Unfiltered Henderson's Best Amber Ale w. Canadian Whiskey Soaked Figs & Cocoa Nibs",
    "region": "Ontario",
    "style": "Amber Ale"
  },
  {
    "id": 280,
    "brewery": "High Park Brewery",
    "name": "Across the Pond English Special Ale",
    "region": "Ontario",
    "style": "Traditional ESB"
  },
  {
    "id": 281,
    "brewery": "Hockley Valley Brewing Company",
    "name": "Caskus Clay -Thrilla w. Vanilla",
    "region": "Ontario",
    "style": "English Ale"
  },
  {
    "id": 282,
    "brewery": "Hockley Valley Brewing Company",
    "name": "Outlandish Bee In Amber",
    "region": "Ontario",
    "style": "Amber Ale"
  },
  {
    "id": 283,
    "brewery": "Indie Ale House",
    "name": "Breakfast Porter",
    "region": "Ontario",
    "style": "Porter"
  },
  {
    "id": 284,
    "brewery": "Indie Ale House",
    "name": "Strawberry Instigator IPA",
    "region": "Ontario",
    "style": "Fruit IPA"
  },
  {
    "id": 285,
    "brewery": "Indie Ale House",
    "name": "Brett IPA",
    "region": "Ontario",
    "style": "American IPA w. Brett."
  },
  {
    "id": 286,
    "brewery": "Indie Ale House",
    "name": "Raffaele",
    "region": "Ontario",
    "style": "American IPA w. Equinox Hops"
  },
  {
    "id": 287,
    "brewery": "Junction Craft Brewing",
    "name": "Stoked & Smoked",
    "region": "Ontario",
    "style": "English Mild"
  },
  {
    "id": 288,
    "brewery": "Junction Craft Brewing",
    "name": "DESTRUCTOR",
    "region": "Ontario",
    "style": "Cascadian Dark"
  },
  {
    "id": 289,
    "brewery": "Kensington Brewhouse",
    "name": "Bonfire",
    "region": "Ontario",
    "style": "Rye Session Stout w. Roasted Marshmallows"
  },
  {
    "id": 290,
    "brewery": "Leftfield Brewery",
    "name": "Go Ahead",
    "region": "Ontario",
    "style": "German Sour Wheat w. Raspberries & Hibiscus"
  },
  {
    "id": 291,
    "brewery": "Leftfield Brewery",
    "name": "Midnight Sun Game",
    "region": "Ontario",
    "style": "Dark American Wheat"
  },
  {
    "id": 292,
    "brewery": "Louis Cifer Brew Works",
    "name": "Darkhorse Espresso APA",
    "region": "Ontario",
    "style": "Single Hop APA w. Espresso"
  },
  {
    "id": 293,
    "brewery": "Louis Cifer Brew Works",
    "name": "Detox",
    "region": "Ontario",
    "style": "American Double IPA"
  },
  {
    "id": 294,
    "brewery": "Louis Cifer Brew Works",
    "name": "Ukrainian Imperial Stout",
    "region": "Ontario",
    "style": "Imperial stout w. Vanilla & Sour Cherry"
  },
  {
    "id": 295,
    "brewery": "MacKinnon Brothers Brewing",
    "name": "Red Fox Radler",
    "region": "Ontario",
    "style": "Summer Ale"
  },
  {
    "id": 296,
    "brewery": "MacKinnon Brothers Brewing",
    "name": "Honey 8Man",
    "region": "Ontario",
    "style": "English Pale Ale"
  },
  {
    "id": 297,
    "brewery": "MacLean's Ales Inc",
    "name": "MacLean's ESB",
    "region": "Ontario",
    "style": "Extra Special Bitter"
  },
  {
    "id": 298,
    "brewery": "Manantler Craft Brewing Co.",
    "name": "Liquid Swords",
    "region": "Ontario",
    "style": "American IPA w. Pineapple"
  },
  {
    "id": 299,
    "brewery": "Mill Street Brewery",
    "name": "Witches' Knickers",
    "region": "Ontario",
    "style": "English IPA"
  },
  {
    "id": 300,
    "brewery": "Mill Street Brewery",
    "name": "Frambozen Raspberry Ale",
    "region": "Ontario",
    "style": "Belgian Style Wheat"
  },
  {
    "id": 301,
    "brewery": "Muddy York Brewing Co.",
    "name": "Muddy York Chai Porter",
    "region": "Ontario",
    "style": "Spiced Porter"
  },
  {
    "id": 302,
    "brewery": "Muskoka Brewery",
    "name": "One Bomb",
    "region": "Ontario",
    "style": "Double IPA"
  },
  {
    "id": 303,
    "brewery": "Niagara Oast House Brewers",
    "name": "Niagara Verjus Sour Ale",
    "region": "Ontario",
    "style": "Golden Sour w. Verjus"
  },
  {
    "id": 304,
    "brewery": "Niagara Oast House Brewers",
    "name": "Maple Bacon Stout",
    "region": "Ontario",
    "style": "Foreign Extra Stout w. Maple Syrup & Bacon"
  },
  {
    "id": 305,
    "brewery": "Nickel Brook Brewing Co",
    "name": "Uncommon Element",
    "region": "Ontario",
    "style": "Brett Pale Ale"
  },
  {
    "id": 306,
    "brewery": "Nickel Brook Brewing Co",
    "name": "Naughty Neighbour",
    "region": "Ontario",
    "style": "American Pale Ale"
  },
  {
    "id": 307,
    "brewery": "Nickel Brook Brewing Co",
    "name": "Ceres",
    "region": "Ontario",
    "style": "Cucumber & Lime Gose"
  },
  {
    "id": 308,
    "brewery": "Northwinds Brewery",
    "name": "Rad Dog",
    "region": "Ontario",
    "style": "Belgian Pale Ale"
  },
  {
    "id": 309,
    "brewery": "Northwinds Brewery",
    "name": "Gatekeeper",
    "region": "Ontario",
    "style": "Belgian IPA"
  },
  {
    "id": 310,
    "brewery": "Pitschfork Brewing",
    "name": "Pitsch Perfect Pilsner",
    "region": "Ontario",
    "style": "Unfiltered German Style Pilsner"
  },
  {
    "id": 311,
    "brewery": "Pitschfork Brewing",
    "name": "Fistful Of Festbier",
    "region": "Ontario",
    "style": "Munich Style Festbier"
  },
  {
    "id": 312,
    "brewery": "Rainhard Brewing Co.",
    "name": "Double KaPow!",
    "region": "Ontario",
    "style": "Double IPA"
  },
  {
    "id": 313,
    "brewery": "Redline Brewhouse",
    "name": "Southern Hospitality",
    "region": "Ontario",
    "style": "Sweet Potato Ale w. Brown Sugar, Marshmallow, & Pecans"
  },
  {
    "id": 314,
    "brewery": "Redline Brewhouse",
    "name": "Clutch w. Apricot & Peach",
    "region": "Ontario",
    "style": "American Pale Ale"
  },
  {
    "id": 315,
    "brewery": "Royal City Brewing Co.",
    "name": "Pining For The Fjords",
    "region": "Ontario",
    "style": "Norwegian Farmhouse Ale"
  },
  {
    "id": 316,
    "brewery": "Royal City Brewing Co.",
    "name": "Earl Grey Porter",
    "region": "Ontario",
    "style": "Tea Infused Porter"
  },
  {
    "id": 317,
    "brewery": "Sawdust City Brewing Company",
    "name": "Fiebre De Calabaza",
    "region": "Ontario",
    "style": "Bourbon Barrel Fermented Mexican Pumpkin Stout"
  },
  {
    "id": 318,
    "brewery": "Sawdust City Brewing Company",
    "name": "11.05 2016",
    "region": "Ontario",
    "style": "Belgian Tripel w. Brett"
  },
  {
    "id": 319,
    "brewery": "Stack Brewing",
    "name": "PIPA",
    "region": "Ontario",
    "style": "Pumpkin IPA"
  },
  {
    "id": 320,
    "brewery": "Stack Brewing",
    "name": "Time Bomb",
    "region": "Ontario",
    "style": "Brett Belgian Ale w. Hibiscus"
  },
  {
    "id": 321,
    "brewery": "Stone City Ales",
    "name": "Ships In The Night w. Raspberries",
    "region": "Ontario",
    "style": "Oatmeal Stout"
  },
  {
    "id": 322,
    "brewery": "Stone City Ales",
    "name": "Grizzled Hipster",
    "region": "Ontario",
    "style": "Double IPA"
  },
  {
    "id": 323,
    "brewery": "Stone City Ales",
    "name": "Patricia",
    "region": "Ontario",
    "style": "Saison w. Squash & Sweet Potato"
  },
  {
    "id": 324,
    "brewery": "Stone City Ales",
    "name": "Everything is Purple",
    "region": "Ontario",
    "style": "Sour Witbier w. Haskap Berries"
  },
  {
    "id": 325,
    "brewery": "Stone City Ales",
    "name": "Conundrum",
    "region": "Ontario",
    "style": "Barrel Aged Sour Brown Ale w. Cherries"
  },
  {
    "id": 326,
    "brewery": "The Collingwood Brewery",
    "name": "Bilbo Flagons",
    "region": "Ontario",
    "style": "Honey Brown Ale"
  },
  {
    "id": 327,
    "brewery": "The Exchange Brewery",
    "name": "De 'Peach' Mode",
    "region": "Ontario",
    "style": "Sour Brown Ale w. Peaches"
  },
  {
    "id": 328,
    "brewery": "The Exchange Brewery",
    "name": "Framboise",
    "region": "Ontario",
    "style": "Belgian Pale Ale w. Raspberries"
  },
  {
    "id": 329,
    "brewery": "The Second Wedge Brewing Company",
    "name": "Monday Morning Wood",
    "region": "Ontario",
    "style": "Scottish-Style Ale"
  },
  {
    "id": 330,
    "brewery": "The Second Wedge Brewing Company",
    "name": "Blackcurrant Porter",
    "region": "Ontario",
    "style": "Porter"
  },
  {
    "id": 331,
    "brewery": "Tooth & Nail Brewing Company",
    "name": "Eerste",
    "region": "Ontario",
    "style": "Blended Barrel-Aged Ale w. Brett."
  },
  {
    "id": 332,
    "brewery": "Tooth & Nail Brewing Company",
    "name": "Tenacity",
    "region": "Ontario",
    "style": "Pale Ale"
  },
  {
    "id": 333,
    "brewery": "Tooth & Nail Brewing Company",
    "name": "Fortified",
    "region": "Ontario",
    "style": "Imperial Stout"
  },
  {
    "id": 334,
    "brewery": "Tooth & Nail Brewing Company",
    "name": "Sucker Punch",
    "region": "Ontario",
    "style": "Double IPA"
  },
  {
    "id": 335,
    "brewery": "Wellington Brewery",
    "name": "Quick Brown Fox",
    "region": "Ontario",
    "style": "ESB"
  },
  {
    "id": 336,
    "brewery": "Wellington Brewery",
    "name": "Ghost Cow: The Way of the Samurai",
    "region": "Ontario",
    "style": "Milk Stout w. Ghost Peppers & Cocoa"
  },
  {
    "id": 337,
    "brewery": "Mark Verok (@ Rainhard Brewing Co) Vanilla Gorilla",
    "name": "Vanilla Coconut Porter",
    "region": "Homebrews",
    "style": "Vanilla Coconut Porter"
  },
  {
    "id": 338,
    "brewery": "John Jenkinson (@ Forked River) Chocolate Doom,",
    "name": "American Stout w Bourbon Soaked Cocoa Nibs & Vanilla Beans",
    "region": "Homebrews",
    "style": "American Stout"
  },
  {
    "id": 339,
    "brewery": "Chris Saunders & Virginie Corneau (@ Folly Brewpub) Wit Male Tears",
    "name": "Gose",
    "region": "Homebrews",
    "style": "Gose"
  },
  {
    "id": 340,
    "brewery": "Guillaume Couture-Levesque & Pamela McBride (@ Halo Brewery) Trust Fam",
    "name": "English Mild w. Blackberries",
    "region": "Homebrews",
    "style": "English Mild"
  },
  {
    "id": 341,
    "brewery": "Nick Hodowsky (@ Indie Ale House) Spreadsheets & Rye",
    "name": "Irish Extra Rye Stout",
    "region": "Homebrews",
    "style": "Irish Extra Rye Stout"
  },
  {
    "id": 342,
    "brewery": "Sean Owen (@ Halo Brewery) V2.0 Bottle Rocket,",
    "name": "American IPA",
    "region": "Homebrews",
    "style": "American IPA"
  },
  {
    "id": 343,
    "brewery": "Michael Naish (@ Forked River) The Hunter",
    "name": "American Porter",
    "region": "Homebrews",
    "style": "American Porter"
  },
  {
    "id": 344,
    "brewery": "Quincy Jermyn (@ Henderson Brewing Co) Pucked Up",
    "name": "Sour Brett Pale Ale",
    "region": "Homebrews",
    "style": "Sour Brett Pale Ale"
  },
  {
    "id": 345,
    "brewery": "Steve Pilotto (@ Granite Brewery) Wild Turkey IPA",
    "name": "American IPA w. Ontario Wild Turkey Hops",
    "region": "Homebrews",
    "style": "Azacca, & Cascade"
  },
  {
    "id": 346,
    "brewery": "Mark Samborski (@ Henderson Brewing Co.)",
    "name": "Borski's Best Bitter",
    "region": "Homebrews",
    "style": "Best Bitter"
  },
  {
    "id": 347,
    "brewery": "GTA Brews (@ Henderson Brewing Co) Grandma Lucile's Libation",
    "name": "Apple Pie Ale",
    "region": "Homebrews",
    "style": "Apple Pie Ale"
  },
  {
    "id": 348,
    "brewery": "Eric Cousineau (@ Henderson Brewing Co) Kentucky Common",
    "name": "Kentucky Common",
    "region": "Homebrews",
    "style": "Kentucky Common"
  },
  {
    "id": 349,
    "brewery": "Zack Weinberg & Eric Ecclestone (@ Great Lakes) What a Time",
    "name": "Cinnamon Raisin Oatmeal Brown Ale w. Vermont Ale Yeast",
    "region": "Homebrews",
    "style": "Cinnamon Raisin Oatmeal Brown Ale"
  },
  {
    "id": 350,
    "brewery": "Eric Emery & Danny Pimenta (@ Common Good Brewery) Zest on the Beach",
    "name": "Pale Ale w. Fresh Citrus Zest",
    "region": "Homebrews",
    "style": "Pale Ale"
  },
  {
    "id": 351,
    "brewery": "Mike Capiak & JP Tibensky (@ Common Good Brewery) 5am in Toronto",
    "name": "Black IPA .Fresh Citrus Zest",
    "region": "Homebrews",
    "style": "Black IPA"
  },
  {
    "id": 352,
    "brewery": "101 Cider House",
    "name": "Island Hopper",
    "region": "Cider",
    "style": "Sour Cider w. Gauva, Passionfruit & Citra Hops"
  },
  {
    "id": 353,
    "brewery": "101 Cider House",
    "name": "Fire & Ashes",
    "region": "Cider",
    "style": "Sriracha, Sour Cider w. Lemon Verbena, Blood Orange & Activated Charcoal"
  },
  {
    "id": 354,
    "brewery": "101 Cider House",
    "name": "Black Hop Down",
    "region": "Cider",
    "style": "Sour Cider Dry Hopped w. Citra & Activated Charcoal"
  },
  {
    "id": 355,
    "brewery": "Cider Creek",
    "name": "D'Crango Unchained",
    "region": "Cider",
    "style": "Cider"
  },
  {
    "id": 356,
    "brewery": "Duxbury Cider",
    "name": "Heritage 1650",
    "region": "Cider",
    "style": "North American Cider"
  },
  {
    "id": 357,
    "brewery": "Duxbury Cider",
    "name": "Tilted Barn",
    "region": "Cider",
    "style": "Dry Hopped Cider"
  },
  {
    "id": 358,
    "brewery": "Embark Craft Ciderworks",
    "name": "Farmhouse Raspberry Cider",
    "region": "Cider",
    "style": "Farmhouse Raspberry Cider"
  },
  {
    "id": 359,
    "brewery": "Embark Craft Ciderworks",
    "name": "Farmhouse Barrel Aged Cider",
    "region": "Cider",
    "style": "Farmhouse Barrel Aged Cider"
  },
  {
    "id": 360,
    "brewery": "Ernest Cider Co.",
    "name": "Cherriots of Fire",
    "region": "Cider",
    "style": "Bourbon Barrel Aged Cider w. Black Cherries, Cloves, Pink Peppercorns & Cinnamon"
  },
  {
    "id": 361,
    "brewery": "Ernest Cider Co.",
    "name": "Key West",
    "region": "Cider",
    "style": "Dry Hopped Cider w. Key Limes, Lemongrass & Liquorice"
  },
  {
    "id": 362,
    "brewery": "Ernest Cider Co.",
    "name": "Hopiphany",
    "region": "Cider",
    "style": "Dry Hopped Cider w. Ontario Fresh Cranberries"
  },
  {
    "id": 363,
    "brewery": "Ernest Cider Co.",
    "name": "Wilderbean",
    "region": "Cider",
    "style": "Bourbon Barrel Aged Cider w. Ontario Wild Blueberries, Saffron & Madagascar Vanilla Beans"
  },
  {
    "id": 364,
    "brewery": "Ironwood Hard Cider",
    "name": "Hopped Up On Razzies",
    "region": "Cider",
    "style": "Dry Hopped Cider w. Cascade & Raspbery"
  },
  {
    "id": 365,
    "brewery": "Ironwood Hard Cider",
    "name": "Szechuan Love",
    "region": "Cider",
    "style": "Red-Fleshed Apple Cider w. Szechuan Pepper"
  },
  {
    "id": 366,
    "brewery": "Les Vergers De La Colline",
    "name": "Cuivre Fut De Chene",
    "region": "Cider",
    "style": "Wood Aged Cider"
  },
  {
    "id": 367,
    "brewery": "Les Vergers De La Colline",
    "name": "Honeycrisp Sour",
    "region": "Cider",
    "style": "Brett Crabbple Cider"
  },
  {
    "id": 368,
    "brewery": "Les Vergers De La Colline",
    "name": "Api-Hop",
    "region": "Cider",
    "style": "Hopped Cider"
  },
  {
    "id": 369,
    "brewery": "Les Vergers De La Colline",
    "name": "Galaxy Cider",
    "region": "Cider",
    "style": "Hopped Cider"
  },
  {
    "id": 370,
    "brewery": "Les Vergers De La Colline",
    "name": "Bouche 2015",
    "region": "Cider",
    "style": "Bouche Traditional Cider"
  },
  {
    "id": 371,
    "brewery": "Les Vergers De La Colline",
    "name": "Apple Tea",
    "region": "Cider",
    "style": "Tea Cider"
  },
  {
    "id": 372,
    "brewery": "Pommies Cider Co.",
    "name": "Cherrio",
    "region": "Cider",
    "style": "Apple Cider w. Ontario Sour Cherries & Ontario Heritage Apples"
  },
  {
    "id": 373,
    "brewery": "Pommies Cider Co.",
    "name": "Mac Daddy",
    "region": "Cider",
    "style": "Apple Cider w. Mcintosh Apples Aged for 2 Years"
  },
  {
    "id": 374,
    "brewery": "Pommies Cider Co.",
    "name": "Life's a Peach",
    "region": "Cider",
    "style": "Apple Cider w. Ontario Peaches & Rosemary"
  },
  {
    "id": 375,
    "brewery": "Pommies Cider Co.",
    "name": "Wild Perry",
    "region": "Cider",
    "style": "Pear Cider w. Wild Yeast"
  },
  {
    "id": 376,
    "brewery": "Pommies Cider Co.",
    "name": "Pommies Farmhouse",
    "region": "Cider",
    "style": "Farmhouse Cider"
  },
  {
    "id": 377,
    "brewery": "Revel Cider",
    "name": "Pear Necessitites",
    "region": "Cider",
    "style": "Perry Cider w. Sauvignon Blanc Yeast"
  },
  {
    "id": 378,
    "brewery": "Revel Cider",
    "name": "Lucy's Orange Beret",
    "region": "Cider",
    "style": "Zero Sugar Cider w. Citra & Oranges"
  },
  {
    "id": 379,
    "brewery": "Revel Cider",
    "name": "Tepache",
    "region": "Cider",
    "style": "Mexcian Style Cider w. Pineapple, Clove, Cinnamon"
  },
  {
    "id": 380,
    "brewery": "Revel Cider",
    "name": "Lime Apfelgose",
    "region": "Cider",
    "style": "Apfelgose w. Lacto, Sea Salt, Corriander & Lime"
  },
  {
    "id": 381,
    "brewery": "Revel Cider",
    "name": "Red White & Bugs",
    "region": "Cider",
    "style": "Wild Fermented Cider Blended From Red/White Wine Barrels"
  },
  {
    "id": 382,
    "brewery": "Revel Cider",
    "name": "Bittersweet Freedom",
    "region": "Cider",
    "style": "Wild Cider Aged w. Malolactic Bacteria"
  },
  {
    "id": 383,
    "brewery": "Revel Cider",
    "name": "Roses are Red",
    "region": "Cider",
    "style": "Cider w. Rose Petals & Hibiscus"
  },
  {
    "id": 384,
    "brewery": "Revel Cider",
    "name": "Mango Earl",
    "region": "Cider",
    "style": "Cider w. Mango & Earl Grey"
  },
  {
    "id": 385,
    "brewery": "Revel Cider",
    "name": "Spirit of India",
    "region": "Cider",
    "style": "Cider w. Gin Botanicals & Tamarind"
  },
  {
    "id": 386,
    "brewery": "Revel Cider",
    "name": "Lucy's Lucid Dream",
    "region": "Cider",
    "style": "Tart Cider Dry Hopped w. Citra & Hop X"
  },
  {
    "id": 387,
    "brewery": "Reverend Nat's Hard Cider",
    "name": "Lorrie's Gold",
    "region": "Cider",
    "style": "Cider"
  },
  {
    "id": 388,
    "brewery": "Reverend Nat's Hard Cider",
    "name": "Shoot The Glass",
    "region": "Cider",
    "style": "Cider"
  },
  {
    "id": 389,
    "brewery": "Reverend Nat's Hard Cider",
    "name": "Revelation Newtown Pippin",
    "region": "Cider",
    "style": "Cider"
  },
  {
    "id": 390,
    "brewery": "Spirit Tree Estate Cidery",
    "name": "BBQ Smoke",
    "region": "Cider",
    "style": "New England Cider"
  },
  {
    "id": 391,
    "brewery": "Spirit Tree Estate Cidery",
    "name": "Gr&pa's GoGo Juice",
    "region": "Cider",
    "style": "Hopped Scrumpy"
  },
  {
    "id": 392,
    "brewery": "Spirit Tree Estate Cidery",
    "name": "Pumpkin Chai",
    "region": "Cider",
    "style": "Speciality Infused Cider"
  },
  {
    "id": 393,
    "brewery": "Spirit Tree Estate Cidery",
    "name": "Sour Cherry Pear",
    "region": "Cider",
    "style": "Fruit Flavoured Pear Cider"
  },
  {
    "id": 394,
    "brewery": "Spirit Tree Estate Cidery",
    "name": "Purple Rain",
    "region": "Cider",
    "style": "Fruit/Veg Flavoured Cider w. Black Currants & Beet Juice"
  },
  {
    "id": 395,
    "brewery": "Spirit Tree Estate Cidery",
    "name": "Flaming Peach",
    "region": "Cider",
    "style": "Fruit Flavoured Cider"
  },
  {
    "id": 396,
    "brewery": "Spirit Tree Estate Cidery",
    "name": "Double Pagan",
    "region": "Cider",
    "style": "Oak Aged Rose Cider w. Herbs"
  },
  {
    "id": 397,
    "brewery": "Spirit Tree Estate Cidery",
    "name": "WTF Hopped Cider",
    "region": "Cider",
    "style": "Hopped Cider"
  },
  {
    "id": 398,
    "brewery": "Spirit Tree Estate Cidery",
    "name": "Funky Old Scrumpy",
    "region": "Cider",
    "style": "Unfiltered English Farmhouse Cider"
  },
  {
    "id": 399,
    "brewery": "Spirit Tree Estate Cidery",
    "name": "Hopped Chesnut Crapabble",
    "region": "Cider",
    "style": "Hopped Cider w. Crabapple"
  },
  {
    "id": 400,
    "brewery": "West Ave Cider",
    "name": "Barrett Fuller's Secret",
    "region": "Cider",
    "style": "Bourbon Barrel Aged Cider"
  },
  {
    "id": 401,
    "brewery": "West Ave Cider",
    "name": "Gold Dust",
    "region": "Cider",
    "style": "Single Variety Golden Russet Apple Cider"
  },
  {
    "id": 402,
    "brewery": "West Ave Cider",
    "name": "Legend (of the Fall) 2015",
    "region": "Cider",
    "style": "Farmhouse Cider"
  },
  {
    "id": 403,
    "brewery": "West Ave Cider",
    "name": "SlaughterMelon",
    "region": "Cider",
    "style": "Watermelon & Apple Cider"
  },
  {
    "id": 404,
    "brewery": "West Ave Cider",
    "name": "The Catalyst MK III: Hopped Peach Cider",
    "region": "Cider",
    "style": "Hopped Peach Cider"
  },
  {
    "id": 405,
    "brewery": "West Ave Cider",
    "name": "SPY",
    "region": "Cider",
    "style": "Single Variety Northern Spy Apple Cider"
  },
  {
    "id": 406,
    "brewery": "West Ave Cider",
    "name": "Staghorn",
    "region": "Cider",
    "style": "Sumac Cider"
  },
  {
    "id": 407,
    "brewery": "West Ave Cider",
    "name": "The Switch",
    "region": "Cider",
    "style": "Cabernet Franc & Apple Cider"
  },
  {
    "id": 408,
    "brewery": "West Ave Cider",
    "name": "Heritage Funk",
    "region": "Cider",
    "style": "Farmhouse Cider"
  },
  {
    "id": 409,
    "brewery": "West Ave Cider",
    "name": "Cherriosity",
    "region": "Cider",
    "style": "Niagara Montmorency Cherry Cider"
  },
  {
    "id": 410,
    "brewery": "Amsterdam Brewery",
    "name": "Bad Life Decisions",
    "region": "IPA Challenge",
    "style": "American IPA"
  },
  {
    "id": 411,
    "brewery": "Bad Apple",
    "name": "Box Cutter",
    "region": "IPA Challenge",
    "style": "American IPA"
  },
  {
    "id": 412,
    "brewery": "Barnstormer Brewing Co.",
    "name": "Flight Delay",
    "region": "IPA Challenge",
    "style": "American IPA"
  },
  {
    "id": 413,
    "brewery": "BATCH",
    "name": "India Pale Ale",
    "region": "IPA Challenge",
    "style": "American IPA"
  },
  {
    "id": 414,
    "brewery": "Benelux",
    "name": "Sabotage",
    "region": "IPA Challenge",
    "style": "American IPA"
  },
  {
    "id": 415,
    "brewery": "Brasserie Dunham",
    "name": "Cyclope Theta",
    "region": "IPA Challenge",
    "style": "American IPA"
  },
  {
    "id": 416,
    "brewery": "Collective Arts",
    "name": "Ransack the Universe",
    "region": "IPA Challenge",
    "style": "American IPA"
  },
  {
    "id": 417,
    "brewery": "Driftwood",
    "name": "Fat Tug",
    "region": "IPA Challenge",
    "style": "Northwest IPA"
  },
  {
    "id": 418,
    "brewery": "Flying Monkeys",
    "name": "Hoppy Minaj",
    "region": "IPA Challenge",
    "style": "American IPA"
  },
  {
    "id": 419,
    "brewery": "Folly Brewing",
    "name": "Double Dry Hopped Imposter Syndrome",
    "region": "IPA Challenge",
    "style": "Farmhouse IPA"
  },
  {
    "id": 420,
    "brewery": "Forked River Brewing Company",
    "name": "Catch 23",
    "region": "IPA Challenge",
    "style": "Northeast IPA"
  },
  {
    "id": 421,
    "brewery": "Granite Brewery",
    "name": "Hopping Mad",
    "region": "IPA Challenge",
    "style": "American IPA"
  },
  {
    "id": 422,
    "brewery": "Great Lakes Brewery",
    "name": "Karma Citra",
    "region": "IPA Challenge",
    "style": "American IPA"
  },
  {
    "id": 423,
    "brewery": "High Park Brewery",
    "name": "Off the Leash",
    "region": "IPA Challenge",
    "style": "American IPA"
  },
  {
    "id": 424,
    "brewery": "Hopfenstark",
    "name": "Postcolonial",
    "region": "IPA Challenge",
    "style": "Amercian IPA"
  },
  {
    "id": 425,
    "brewery": "Indie Alehouse",
    "name": "Instigator",
    "region": "IPA Challenge",
    "style": "American IPA"
  },
  {
    "id": 426,
    "brewery": "Junction Craft Brewing",
    "name": "Engineer's",
    "region": "IPA Challenge",
    "style": "English IPA"
  },
  {
    "id": 427,
    "brewery": "Kensington Brewhouse",
    "name": "Homegrown",
    "region": "IPA Challenge",
    "style": "American IPA"
  },
  {
    "id": 428,
    "brewery": "Le Castor",
    "name": "Yakima IPA",
    "region": "IPA Challenge",
    "style": "American IPA"
  },
  {
    "id": 429,
    "brewery": "Leftfield Brewery",
    "name": "Laser Show",
    "region": "IPA Challenge",
    "style": "Vermont Style IPA"
  },
  {
    "id": 430,
    "brewery": "Les Trois Mousquetaires",
    "name": "IPA",
    "region": "IPA Challenge",
    "style": "American IPA"
  },
  {
    "id": 431,
    "brewery": "Manantler Craft Brewing Co",
    "name": "Liquid Swords",
    "region": "IPA Challenge",
    "style": "Amercian IPA"
  },
  {
    "id": 432,
    "brewery": "Mill Street Brewery",
    "name": "West Coast Style IPA",
    "region": "IPA Challenge",
    "style": "American IPA"
  },
  {
    "id": 433,
    "brewery": "Muskoka Brewery",
    "name": "The Spicy Old Man",
    "region": "IPA Challenge",
    "style": "American IPA"
  },
  {
    "id": 434,
    "brewery": "Niagara Oast House Brewers",
    "name": "Bigger Than Yours By A Country Mile",
    "region": "IPA Challenge",
    "style": "American IPA"
  },
  {
    "id": 435,
    "brewery": "Nickelbrook",
    "name": "Headstock",
    "region": "IPA Challenge",
    "style": "American IPA"
  },
  {
    "id": 436,
    "brewery": "Rainhard Brewing Co.",
    "name": "KaPow! American IPA",
    "region": "IPA Challenge",
    "style": "American IPA"
  },
  {
    "id": 437,
    "brewery": "Redline Brewhouse",
    "name": "Dennis is Bastard Man",
    "region": "IPA Challenge",
    "style": "American IPA"
  },
  {
    "id": 438,
    "brewery": "Stone City Ales",
    "name": "Uncharted",
    "region": "IPA Challenge",
    "style": "American IPA"
  },
  {
    "id": 439,
    "brewery": "The Collingwood Brewery",
    "name": "Market Garden",
    "region": "IPA Challenge",
    "style": "American IPA"
  },
  {
    "id": 440,
    "brewery": "Tooth & Nail Brewing Company",
    "name": "Rabble Rouser",
    "region": "IPA Challenge",
    "style": "American IPA"
  },
  {
    "id": 441,
    "brewery": "Unflitered",
    "name": "Exile On North St",
    "region": "IPA Challenge",
    "style": "American IPA"
  }
]
